telegram_ai_agent/__init__.py
telegram_ai_agent/agent.py
telegram_ai_agent/config.py
telegram_ai_agent/inbound.py
telegram_ai_agent/messages_handler.py
telegram_ai_agent/outbound.py
telegram_ai_agent/session.py
telegram_ai_agent/tools.py
telegram_ai_agent/utils.py
telegram_ai_agent-0.1.1.dist-info/METADATA
telegram_ai_agent-0.1.1.dist-info/WHEEL
telegram_ai_agent-0.1.1.dist-info/RECORD
