Metadata-Version: 2.1
Name: telegram-ai-agent
Version: 0.1.1
Summary: A Python library for managing Telegram AI agents with outbound and inbound messaging capabilities
Author: Ivan Fokeev
Author-email: vanya@vanya.cc
Requires-Python: >=3.11,<4.0
Classifier: Programming Language :: Python :: 3
Classifier: Programming Language :: Python :: 3.11
Requires-Dist: httpx (>=0.27.2,<0.28.0)
Requires-Dist: langchain (>=0.3.1,<0.4.0)
Requires-Dist: langchain-experimental (>=0.3.2,<0.4.0)
Requires-Dist: openai (>=1.49.0,<2.0.0)
Requires-Dist: pandas (>=2.2.3,<3.0.0)
Requires-Dist: phidata (>=2.4.37,<3.0.0)
Requires-Dist: pysocks (>=1.7.1,<2.0.0)
Requires-Dist: python-dotenv (>=1.0.1,<2.0.0)
Requires-Dist: python-socks[asyncio] (>=2.5.3,<3.0.0)
Requires-Dist: sqlalchemy (>=2.0.35,<3.0.0)
Requires-Dist: streamlit (>=1.38.0,<2.0.0)
Requires-Dist: telethon (>=1.37.0,<2.0.0)
Requires-Dist: tiktoken (>=0.7.0,<0.8.0)
